pyprocs.py
pyprocs-0.1.1.dist-info/LICENSE
pyprocs-0.1.1.dist-info/METADATA
pyprocs-0.1.1.dist-info/WHEEL
pyprocs-0.1.1.dist-info/top_level.txt
pyprocs-0.1.1.dist-info/RECORD
