Metadata-Version: 2.1
Name: pyprocs
Version: 0.1.1
Summary: Multiprocess manager
Home-page: https://github.com/guyingbo/pyprocs
Author: Yingbo Gu
Author-email: tensiongyb@gmail.com
Maintainer: Yingbo Gu
Maintainer-email: tensiongyb@gmail.com
License: MIT
Platform: UNKNOWN
Classifier: License :: OSI Approved :: MIT License
Classifier: Programming Language :: Python :: 3.6
Classifier: Programming Language :: Python :: 3.7
Classifier: Intended Audience :: Developers
Requires-Python: >=3.5
Requires-Dist: async-timeout
